examples/__init__.py
examples/plot_graph.py
examples/text_plot_examples.py
id3/__init__.py
id3/export.py
id3/id3.py
id3/node.py
id3/splitter.py
id3/tree.py
id3/data/__init__.py
id3/data/load_data.py
id3/utils/__init__.py
id3/utils/array_operations.py
id3/utils/checks.py
id3/utils/extended_label_encoder.py
decision_tree_id_fork-0.0.15.dist-info/LICENSE
decision_tree_id_fork-0.0.15.dist-info/METADATA
decision_tree_id_fork-0.0.15.dist-info/WHEEL
decision_tree_id_fork-0.0.15.dist-info/top_level.txt
decision_tree_id_fork-0.0.15.dist-info/RECORD
