Metadata-Version: 2.1
Name: decision-tree-id-fork
Version: 0.0.15
Summary: A scikit-learn compatible package for id3 decision tree
Home-page: https://github.com/DekwoKybon/decision-tree-id3
Author: Daniel Pettersson, Otto Nordander
Author-email: svaante@gmail.com, otto.nordander@gmail.com
Project-URL: Bug Tracker, https://github.com/DekwoKybon/decision-tree-id3/issues
Classifier: Programming Language :: Python :: 3
Classifier: License :: OSI Approved :: MIT License
Classifier: Operating System :: OS Independent
Requires-Python: >=3.7
License-File: LICENSE
Requires-Dist: numpy
Requires-Dist: six
Requires-Dist: scikit-learn (>=1.0)
